{
    "Roles": [
        {
            "Path": "/",
            "RoleName": "aws-elasticbeanstalk-ec2-role",
            "RoleId": "AROA52LJDWETCVVBJGIKY",
            "Arn": "arn:aws:iam::949945086246:role/aws-elasticbeanstalk-ec2-role",
            "CreateDate": "2023-07-25T15:11:21Z",
            "AssumeRolePolicyDocument": {
                "Version": "2012-10-17",
                "Statement": [
                    {
                        "Effect": "Allow",
                        "Principal": {
                            "Service": "ec2.amazonaws.com"
                        },
                        "Action": "sts:AssumeRole"
                    }
                ]
            },
            "Description": "Allows EC2 instances to call AWS services on your behalf.",
            "MaxSessionDuration": 3600
        },
        {
            "Path": "/service-role/",
            "RoleName": "aws-elasticbeanstalk-service-role",
            "RoleId": "AROA52LJDWETGCEWYRYPJ",
            "Arn": "arn:aws:iam::949945086246:role/service-role/aws-elasticbeanstalk-service-role",
            "CreateDate": "2023-07-25T15:26:30Z",
            "AssumeRolePolicyDocument": {
                "Version": "2012-10-17",
                "Statement": [
                    {
                        "Effect": "Allow",
                        "Principal": {
                            "Service": "elasticbeanstalk.amazonaws.com"
                        },
                        "Action": "sts:AssumeRole"
                    }
                ]
            },
            "MaxSessionDuration": 3600
        },
        {
            "Path": "/aws-service-role/autoscaling.amazonaws.com/",
            "RoleName": "AWSServiceRoleForAutoScaling",
            "RoleId": "AROA52LJDWETN2TNUX6ZP",
            "Arn": "arn:aws:iam::949945086246:role/aws-service-role/autoscaling.amazonaws.com/AWSServiceRoleForAutoScaling",
            "CreateDate": "2023-07-25T15:32:33Z",
            "AssumeRolePolicyDocument": {
                "Version": "2012-10-17",
                "Statement": [
                    {
                        "Effect": "Allow",
                        "Principal": {
                            "Service": "autoscaling.amazonaws.com"
                        },
                        "Action": "sts:AssumeRole"
                    }
                ]
            },
            "Description": "Default Service-Linked Role enables access to AWS Services and Resources used or managed by Auto Scaling",
            "MaxSessionDuration": 3600
        },
        {
            "Path": "/aws-service-role/ecs.amazonaws.com/",
            "RoleName": "AWSServiceRoleForECS",
            "RoleId": "AROA52LJDWETJA7DGAXCS",
            "Arn": "arn:aws:iam::949945086246:role/aws-service-role/ecs.amazonaws.com/AWSServiceRoleForECS",
            "CreateDate": "2025-10-15T05:00:59Z",
            "AssumeRolePolicyDocument": {
                "Version": "2012-10-17",
                "Statement": [
                    {
                        "Effect": "Allow",
                        "Principal": {
                            "Service": "ecs.amazonaws.com"
                        },
                        "Action": "sts:AssumeRole"
                    }
                ]
            },
            "Description": "Policy to enable Amazon ECS to manage your EC2 instances and related resources.",
            "MaxSessionDuration": 3600
        },
        {
            "Path": "/aws-service-role/elasticache.amazonaws.com/",
            "RoleName": "AWSServiceRoleForElastiCache",
            "RoleId": "AROA52LJDWETCPVTAR6RE",
            "Arn": "arn:aws:iam::949945086246:role/aws-service-role/elasticache.amazonaws.com/AWSServiceRoleForElastiCache",
            "CreateDate": "2025-10-15T05:01:20Z",
            "AssumeRolePolicyDocument": {
                "Version": "2012-10-17",
                "Statement": [
                    {
                        "Effect": "Allow",
                        "Principal": {
                            "Service": "elasticache.amazonaws.com"
                        },
                        "Action": "sts:AssumeRole"
                    }
                ]
            },
            "Description": "This policy allows ElastiCache to manage AWS resources on your behalf as necessary for managing your cache.",
            "MaxSessionDuration": 3600
        },
        {
            "Path": "/aws-service-role/elasticbeanstalk.amazonaws.com/",
            "RoleName": "AWSServiceRoleForElasticBeanstalk",
            "RoleId": "AROA52LJDWETN462OI5XU",
            "Arn": "arn:aws:iam::949945086246:role/aws-service-role/elasticbeanstalk.amazonaws.com/AWSServiceRoleForElasticBeanstalk",
            "CreateDate": "2023-07-25T15:00:25Z",
            "AssumeRolePolicyDocument": {
                "Version": "2012-10-17",
                "Statement": [
                    {
                        "Effect": "Allow",
                        "Principal": {
                            "Service": "elasticbeanstalk.amazonaws.com"
                        },
                        "Action": "sts:AssumeRole"
                    }
                ]
            },
            "Description": "Allows Elastic Beanstalk to create and manage AWS resources on your behalf.",
            "MaxSessionDuration": 3600
        },
        {
            "Path": "/aws-service-role/elasticloadbalancing.amazonaws.com/",
            "RoleName": "AWSServiceRoleForElasticLoadBalancing",
            "RoleId": "AROA52LJDWETMH5S7KRO6",
            "Arn": "arn:aws:iam::949945086246:role/aws-service-role/elasticloadbalancing.amazonaws.com/AWSServiceRoleForElasticLoadBalancing",
            "CreateDate": "2023-07-27T19:07:37Z",
            "AssumeRolePolicyDocument": {
                "Version": "2012-10-17",
                "Statement": [
                    {
                        "Effect": "Allow",
                        "Principal": {
                            "Service": "elasticloadbalancing.amazonaws.com"
                        },
                        "Action": "sts:AssumeRole"
                    }
                ]
            },
            "Description": "Allows ELB to call AWS services on your behalf.",
            "MaxSessionDuration": 3600
        },
        {
            "Path": "/aws-service-role/organizations.amazonaws.com/",
            "RoleName": "AWSServiceRoleForOrganizations",
            "RoleId": "AROA52LJDWETJXYTFGHHI",
            "Arn": "arn:aws:iam::949945086246:role/aws-service-role/organizations.amazonaws.com/AWSServiceRoleForOrganizations",
            "CreateDate": "2024-11-19T04:50:14Z",
            "AssumeRolePolicyDocument": {
                "Version": "2012-10-17",
                "Statement": [
                    {
                        "Effect": "Allow",
                        "Principal": {
                            "Service": "organizations.amazonaws.com"
                        },
                        "Action": "sts:AssumeRole"
                    }
                ]
            },
            "Description": "Service-linked role used by AWS Organizations to enable integration of other AWS services with Organizations.",
            "MaxSessionDuration": 3600
        },
        {
            "Path": "/aws-service-role/rds.amazonaws.com/",
            "RoleName": "AWSServiceRoleForRDS",
            "RoleId": "AROA52LJDWETAK7BUTIIP",
            "Arn": "arn:aws:iam::949945086246:role/aws-service-role/rds.amazonaws.com/AWSServiceRoleForRDS",
            "CreateDate": "2023-07-25T11:04:43Z",
            "AssumeRolePolicyDocument": {
                "Version": "2012-10-17",
                "Statement": [
                    {
                        "Effect": "Allow",
                        "Principal": {
                            "Service": "rds.amazonaws.com"
                        },
                        "Action": "sts:AssumeRole"
                    }
                ]
            },
            "Description": "Allows Amazon RDS to manage AWS resources on your behalf",
            "MaxSessionDuration": 3600
        },
        {
            "Path": "/aws-service-role/sso.amazonaws.com/",
            "RoleName": "AWSServiceRoleForSSO",
            "RoleId": "AROA52LJDWETPWXCGVTQ6",
            "Arn": "arn:aws:iam::949945086246:role/aws-service-role/sso.amazonaws.com/AWSServiceRoleForSSO",
            "CreateDate": "2024-11-19T04:50:16Z",
            "AssumeRolePolicyDocument": {
                "Version": "2012-10-17",
                "Statement": [
                    {
                        "Effect": "Allow",
                        "Principal": {
                            "Service": "sso.amazonaws.com"
                        },
                        "Action": "sts:AssumeRole"
                    }
                ]
            },
            "Description": "Service-linked role used by AWS SSO to manage AWS resources, including IAM roles, policies and SAML IdP on your behalf.",
            "MaxSessionDuration": 3600
        },
        {
            "Path": "/aws-service-role/support.amazonaws.com/",
            "RoleName": "AWSServiceRoleForSupport",
            "RoleId": "AROA52LJDWETF5MYVZG53",
            "Arn": "arn:aws:iam::949945086246:role/aws-service-role/support.amazonaws.com/AWSServiceRoleForSupport",
            "CreateDate": "2023-07-17T05:48:02Z",
            "AssumeRolePolicyDocument": {
                "Version": "2012-10-17",
                "Statement": [
                    {
                        "Effect": "Allow",
                        "Principal": {
                            "Service": "support.amazonaws.com"
                        },
                        "Action": "sts:AssumeRole"
                    }
                ]
            },
            "Description": "Enables resource access for AWS to provide billing, administrative and support services",
            "MaxSessionDuration": 3600
        },
        {
            "Path": "/aws-service-role/trustedadvisor.amazonaws.com/",
            "RoleName": "AWSServiceRoleForTrustedAdvisor",
            "RoleId": "AROA52LJDWETBQXDVUCKT",
            "Arn": "arn:aws:iam::949945086246:role/aws-service-role/trustedadvisor.amazonaws.com/AWSServiceRoleForTrustedAdvisor",
            "CreateDate": "2023-07-17T05:48:02Z",
            "AssumeRolePolicyDocument": {
                "Version": "2012-10-17",
                "Statement": [
                    {
                        "Effect": "Allow",
                        "Principal": {
                            "Service": "trustedadvisor.amazonaws.com"
                        },
                        "Action": "sts:AssumeRole"
                    }
                ]
            },
            "Description": "Access for the AWS Trusted Advisor Service to help reduce cost, increase performance, and improve security of your AWS environment.",
            "MaxSessionDuration": 3600
        },
        {
            "Path": "/",
            "RoleName": "dynamodb-access",
            "RoleId": "AROA52LJDWETASDIQUANK",
            "Arn": "arn:aws:iam::949945086246:role/dynamodb-access",
            "CreateDate": "2025-10-13T07:04:46Z",
            "AssumeRolePolicyDocument": {
                "Version": "2012-10-17",
                "Statement": [
                    {
                        "Effect": "Allow",
                        "Principal": {
                            "AWS": "arn:aws:iam::949945086246:user/prasanna@carbonmint.com"
                        },
                        "Action": "sts:AssumeRole"
                    }
                ]
            },
            "Description": "",
            "MaxSessionDuration": 3600
        },
        {
            "Path": "/",
            "RoleName": "eb-service-role-upscpro",
            "RoleId": "AROA52LJDWETGZG4MLKDI",
            "Arn": "arn:aws:iam::949945086246:role/eb-service-role-upscpro",
            "CreateDate": "2024-01-17T09:33:46Z",
            "AssumeRolePolicyDocument": {
                "Version": "2012-10-17",
                "Statement": [
                    {
                        "Sid": "",
                        "Effect": "Allow",
                        "Principal": {
                            "Service": "elasticbeanstalk.amazonaws.com"
                        },
                        "Action": "sts:AssumeRole",
                        "Condition": {
                            "StringEquals": {
                                "sts:ExternalId": "elasticbeanstalk"
                            }
                        }
                    }
                ]
            },
            "Description": "Allows Elastic Beanstalk to create and manage AWS resources on your behalf.",
            "MaxSessionDuration": 3600
        },
        {
            "Path": "/",
            "RoleName": "rds-monitoring-role",
            "RoleId": "AROA52LJDWETMJEWBUAXM",
            "Arn": "arn:aws:iam::949945086246:role/rds-monitoring-role",
            "CreateDate": "2023-07-25T11:04:39Z",
            "AssumeRolePolicyDocument": {
                "Version": "2012-10-17",
                "Statement": [
                    {
                        "Sid": "",
                        "Effect": "Allow",
                        "Principal": {
                            "Service": "monitoring.rds.amazonaws.com"
                        },
                        "Action": "sts:AssumeRole"
                    }
                ]
            },
            "MaxSessionDuration": 3600
        }
    ]
}
